CHANGELOG.md
proximity/__init__.py
proximity/convenience.py
proximity/mock_trimesh.py
proximity/vendor/README.md
proximity/vendor/__init__.py
proximity/vendor/caching.py
proximity/vendor/constants.py
proximity/vendor/grouping.py
proximity/vendor/parent.py
proximity/vendor/points.py
proximity/vendor/proximity.py
proximity/vendor/triangles.py
proximity/vendor/util.py
proximity-2.0.1.dist-info/LICENSE
proximity-2.0.1.dist-info/WHEEL
proximity-2.0.1.dist-info/METADATA
proximity-2.0.1.dist-info/RECORD
